dash_tailwind_component/NavBar.py
dash_tailwind_component/__init__.py
dash_tailwind_component/_imports_.py
dash_tailwind_component/dash_tailwind_component.min.js
dash_tailwind_component/dash_tailwind_component.min.js.map
dash_tailwind_component/metadata.json
dash_tailwind_component/package-info.json
dash_tailwind_component-0.0.1.dist-info/LICENSE
dash_tailwind_component-0.0.1.dist-info/METADATA
dash_tailwind_component-0.0.1.dist-info/WHEEL
dash_tailwind_component-0.0.1.dist-info/top_level.txt
dash_tailwind_component-0.0.1.dist-info/RECORD
